paudel_test/cli.py
paudel_test/paudel_test.py
paudel_test/__init__.py
paudel_test-0.1.0.dist-info/DESCRIPTION.rst
paudel_test-0.1.0.dist-info/entry_points.txt
paudel_test-0.1.0.dist-info/METADATA
paudel_test-0.1.0.dist-info/metadata.json
paudel_test-0.1.0.dist-info/RECORD
paudel_test-0.1.0.dist-info/top_level.txt
paudel_test-0.1.0.dist-info/WHEEL
