Metadata-Version: 2.0
Name: paudel-test
Version: 0.1.0
Summary: It contains a test file that needed to run the system
Home-page: https://github.com/paudelra/paudel_test
Author: Rajiv Paudel
Author-email: paudelra@msu.edu
License: GNU General Public License v3
Keywords: paudel_test
Platform: UNKNOWN
Classifier: Development Status :: 2 - Pre-Alpha
Classifier: Intended Audience :: Developers
Classifier: License :: OSI Approved :: GNU General Public License v3 (GPLv3)
Classifier: Natural Language :: English
Classifier: Programming Language :: Python :: 2
Classifier: Programming Language :: Python :: 2.6
Classifier: Programming Language :: Python :: 2.7
Classifier: Programming Language :: Python :: 3
Classifier: Programming Language :: Python :: 3.3
Classifier: Programming Language :: Python :: 3.4
Classifier: Programming Language :: Python :: 3.5
Requires-Dist: Click (>=6.0)
